{
  "total_vagas_processadas": 510,
  "campos_removidos": [
    "experiencia_necessaria"
  ],
  "campos_reorganizados": [
    "responsabilidades",
    "habilidades_requeridas",
    "descricao_completa"
  ],
  "estatisticas": {
    "vagas_por_setor": {
      "ServicoSocial": 12,
      "Telecomunicacoes": 32,
      "Telemarketing": 30,
      "Tecnica": 23,
      "Juridica": 30,
      "Industrial": 22,
      "Engenharia": 20,
      "Comunicacao e marketing": 15,
      "arquitetura e design": 13,
      "pecuaria e veterinaria": 15,
      "Suprimentos": 29,
      "Saude": 23,
      "Informatica": 22,
      "Hotelaria e turismo": 13,
      "Financeira": 30,
      "Educacao": 29,
      "Comercio exterior": 15,
      "Comercial e vendas": 14,
      "Administracao": 123
    },
    "vagas_por_titulo": {
      "Ajudante Geral": 1,
      "Coordenadora De Projeto Social": 1,
      "Assistente Social": 1,
      "Cuidador Social": 1,
      "Monitor De Inclusao": 1,
      "Mediador": 1,
      "Assistente Social Media": 1,
      "Clt Imediato At Acompanhante Terapeutico": 1,
      "Coordenador De Projeto Social": 1,
      "Educador A Social": 1,
      "Assistente Social Sr Uti": 1,
      "Assistente Social Pl Uti": 1,
      "Analista Tecnico De Ti": 1,
      "Tecnico De Redes": 1,
      "Analista De Infraestrutura": 2,
      "Tecnico De Telecomunicacoes": 1,
      "Coordenador De Campo": 1,
      "Fiscal Civil": 1,
      "Administrador De Redes Senior Brasilia Df": 1,
      "Gerente De Suporte Tecnico De Tecnologia Da Informacao": 1,
      "Auxiliar Tecnico Em Telecomunicacoes Brasilia E Regiao": 1,
      "Analista De Telecomunicacoes": 1,
      "Tecnico Em Instalacao De Cftv E Ca": 1,
      "Supervisor De Telecomunicacoes": 1,
      "Tecnico Telecom": 1,
      "Agente De Service Desk": 1,
      "Agente De Service Desk Pcd": 1,
      "Auxiliar Administrativo Atendimento Ao Cliente": 2,
      "Auxiliar De Servicos Gerais": 1,
      "Atendente De Salao": 1,
      "Operador De Cobranca": 1,
      "Atendente": 5,
      "Analista De Relacionamento": 1,
      "Assistente De Atendimento": 1,
      "Jovem Aprendiz Na Area De Atendimento": 1,
      "Agente De Atendimento Ao Cidadao": 1,
      "Auxiliar De Cobranca": 2,
      "Supervisor De Televendas": 1,
      "Auxiliar De Cozinha": 4,
      "Atendente Administrativo": 1,
      "Auxiliar De Suporte Ao Cliente": 1,
      "Atendente De Telemarketing Ativo": 1,
      "Tecnico De Manutencao E Instalacao De Portaria Remota": 1,
      "Instalador Sistemas De Seguranca": 1,
      "Tecnico De Campo": 1,
      "Auxiliar Tecnico": 1,
      "Operador E Manutencista De Estacao De Tratamento De Efluente": 1,
      "Tecnico Em Eletroeletronica Junior": 1,
      "Tecnico Eletronico De Campo": 1,
      "Cadista Projetista": 1,
      "Suporte Tecnico": 1,
      "Tecnico De Suporte De Tecnologia Da Informacao": 1,
      "Assistente De Monitoramento Noc Nivel 1": 1,
      "Tecnico De Suporte De Ti Intermitente": 1,
      "Auxiliar Juridico": 2,
      "Advogado Trabalhista": 1,
      "Advogado Assistente": 1,
      "Advogadoa Fechador De Contrato": 1,
      "Advogado": 4,
      "Advogadoa Em Direito Internacional Privado": 1,
      "Advogadoa Com Experiencia Em Contencioso": 1,
      "Advogadoa Com Experiencia Em Direito Civel": 1,
      "Auxiliar Administrativo Juridico": 1,
      "Assistente De Licitacoes": 1,
      "Supervisor De Licitacao": 1,
      "Analista De Licitacoes": 1,
      "Assistente De Licitacao": 1,
      "Analista De Licitacao": 1,
      "Auxiliar De Licitacao": 1,
      "Auxiliar De Servicos Gerais Limpeza": 1,
      "Ajudante De Producao 98075": 1,
      "Ajudante De Producao 98074": 1,
      "Auxiliar De Producao": 4,
      "Ajudante De Producao Vaga Afirmativa Tambem Para O Publico Pcd 98392": 1,
      "Ajudante De Producao Vaga Afirmativa Tambem Para O Publico Pcd 99543": 1,
      "Assistente Administrativo De Manutencao": 1,
      "Analista De Processos": 1,
      "Supervisor De Manutencao Tecnica De Campo": 1,
      "Ajudante De Producao Vaga Afirmativa Tambem Para O Publico Pcd": 1,
      "Auxiliar De Manutencao Geral": 1,
      "Encarregado Mecanico": 1,
      "Lider De Coleta": 1,
      "Lider De Producao": 2,
      "Encarregado De Obras": 1,
      "Tecnico Eletroeletronico": 1,
      "Engenheiro Instalacoes": 1,
      "Meio Oficial De Refrigeracao": 1,
      "Engenheiro De Minas": 1,
      "Tecnico De Laboratorio": 1,
      "Tecnico De Coleta Sanguinea": 1,
      "Engenheiroa Orcamentista Trainee": 1,
      "Entrevistador De Campo": 1,
      "Coordenador De Merchandising": 2,
      "Assistente De Trade Marketing E Merchandising Regional": 1,
      "Trainee De Marketing Multilife": 1,
      "Social Media Analyst": 1,
      "Auxiliar De Festas": 1,
      "Social Media": 1,
      "Atendimento De Marketing E Publicidade": 1,
      "Comunicacao Social Midia": 1,
      "Auxiliar De Marketing": 1,
      "Promotor De Trade Marketing": 1,
      "Locutor": 1,
      "Assistente De Eventos Medicos Brasilia": 1,
      "Especialista De Produtos": 1,
      "Projetista De Instalacoes Prediais Eletrica E Ou Hidraulica Freelance": 1,
      "Projetista De Instalacoes Prediais Hidraulica": 1,
      "Projetista De Instalacoes Prediais Eletrica": 1,
      "Designer Grafico": 2,
      "Projetista De Moveis Planejados": 1,
      "Tecnico Projetista": 1,
      "Desenhista Projetista": 1,
      "Produtor Cultural": 1,
      "Produtor De Moda": 1,
      "Diagramador": 1,
      "Assistente De Producao Grafica Vaga Afirmativa Tambem Para O Publico Pcd": 1,
      "Coordenador De Estagio": 1,
      "Agronomo": 2,
      "Biologo Sorocaba Sp": 1,
      "Veterinario Fortaleza": 1,
      "Engenheiro De Alimentos Junior": 1,
      "Gerente De Maquinas Agricolas": 1,
      "Engenheiro Quimico": 1,
      "Representante Tecnico De Vendas Substratos": 1,
      "Gerente De Fazenda Leiteira": 1,
      "Engenheiro Agronomo": 2,
      "Microbiologista": 1,
      "Tecnico Agricola": 1,
      "Gerente Agricola": 1,
      "Veterinario Patologista": 1,
      "Analista De Logistica": 2,
      "Auxiliar De Almoxarifado E Administrativo": 1,
      "Auxiliar De Almoxarifado": 2,
      "Auxiliar De Estoque": 2,
      "Estoquista": 4,
      "Lider De Operacoes": 1,
      "Auxiliar De Operacoes Temporario": 1,
      "Auxiliar Logistico E Ajudante Geral Brasilia Df": 1,
      "Analista De Estoque Hospitalar": 1,
      "Lider De Operacoes Logisticas": 1,
      "Lider De Logistica": 2,
      "Analista Compras Jr": 1,
      "Fonoaudiologo": 1,
      "Fisioterapeuta Geral": 1,
      "Auxiliar De Cozinha Fast Food": 1,
      "Depiladora": 1,
      "Auxiliar De Nutricao Temporario": 1,
      "Tecnico De Enfermagem Uti": 1,
      "Tecnico De Enfermagem Nefrologia": 1,
      "Tecnico De Enfermagem Com Experiencia Comprovada Em Oftalmologia": 1,
      "Auxiliar De Estetica": 1,
      "Tecnico De Enfermagem": 3,
      "Flebotomista": 1,
      "Tecnico De Enfermagem Cme Temporario Brasilia Df": 1,
      "Nutricionista De Uan": 1,
      "Analista De Suporte Junior": 1,
      "Auxiliar De Suporte Ao Cliente Grupo Euro": 1,
      "Analista De Dados": 3,
      "Analista De Projetos": 1,
      "Analista De Testes Automatizados": 1,
      "Assistente De Ti": 2,
      "Desenvolvedora Junior Php": 1,
      "Bartender": 1,
      "Auxiliar De Confeitaria": 1,
      "Auxiliar De Cozinha Industrial": 1,
      "Manipulador De Alimentos": 1,
      "Cozinheiro": 1,
      "Atendente De Restaurante Kfc Taguatinga Df": 1,
      "Garcom": 1,
      "Garcom Brasilia": 1,
      "Hostess": 1,
      "Gerente De Restaurante Kfc Taguatinga Df": 1,
      "Atendente Fast Food": 1,
      "Consultor De Viagens": 1,
      "Assistente Administrativo Hospitalar": 2,
      "Escriturario": 1,
      "Auxiliar Contabil": 1,
      "Assistente Departamento Pessoal": 1,
      "Analista Fiscal": 1,
      "Assistente Administrativo Imobiliaria": 1,
      "Analista De Planejamento Senior": 1,
      "Assistente De Projetos E Negocios": 1,
      "Auxiliar De Atendimento Administrativo": 1,
      "Trainee Em Ciencias Contabeis": 1,
      "Analista De Faturamento Hospitalar Brasilia Df": 1,
      "Assistente Administrativo": 5,
      "Gerente De Credito Garantias": 1,
      "Assistente Juridico Brasilia Df": 1,
      "Orcamentista": 1,
      "Inspetor De Alunos Pcd": 1,
      "Assistente De Coordenacao Pedagogica": 1,
      "Professor De Ingles": 2,
      "Professora De Bercario": 1,
      "Monitor De Alunos": 2,
      "Educador Fisico": 3,
      "Professora De Hidroestimulacao": 1,
      "Universitario Para Reforco De Exatas": 1,
      "Educador": 1,
      "Professora Jardim": 1,
      "Monitora Escolar": 1,
      "Instrutor De Treinamento": 1,
      "Assistente Faturamento Despacho Aduaneiro": 1,
      "Assistente De Importacao": 2,
      "Auxiliar De Importacao E Exportacao": 3,
      "Auxiliar De Comercio Exterior": 2,
      "Auxiliar De Exportacao": 1,
      "Assistente De Comercio Exterior": 3,
      "Analista De Comercio Exterior Junior": 1,
      "Analista De Exportacao": 1,
      "Analista De Importacao Pleno": 1,
      "Vendedor": 5,
      "Promotor De Vendas": 2,
      "Vendedor Aeroporto": 1,
      "Vendedor De Loja Da Claro Loja Propria Brasilia Df": 1,
      "Consultor De Relacionamento Agendamento De Consultas E Exames": 1,
      "Atendente Comercial Para Asa Norte Df": 1,
      "Assistente Comercial Trainee": 1,
      "Vendedor Aeroporto Madrugada": 1,
      "Representante De Vendas Externo": 1,
      "Auxiliar Pos Venda Energia Solar": 1,
      "Assistente Comercial": 1,
      "Supervisora De Vendas E Distribuicao Vaga Afirmativa Tambem Para O Publico Pcd 98082": 1,
      "Gerente Comercial Regional": 1,
      "Promotor De Vendas Com Moto Brasilia": 1,
      "Promotor De Vendas Externas Brasilia": 1,
      "Consultora De Vendas Para Instituto De Estetica De Cursos Livres E Pos": 1,
      "Vendedora De Loja Com Experiencia Em Otica E Oftalmologia Para Empresa No Sudoeste": 1,
      "Promotor Motociclista Brasilia": 1,
      "Subgerente De Loja Lanchonete Cafeteria": 1,
      "Analista Cs": 1,
      "Coordenador Comercial Vendas": 1,
      "Auxiliar Administrativo Junior": 1,
      "Recepcionista Administrativo": 1,
      "Consultor De Vendas": 6,
      "Vendedor Loja Chocolate": 1,
      "Recepcionista": 3,
      "Promotor De Vendas Brasilia Df": 1,
      "Promotor De Vendas Goiania Go": 1,
      "Vendedor Externo Brasilia Df": 1,
      "Vendedor Externo": 3,
      "Auxiliar Administrativo": 5,
      "Atendente De Vendas": 1,
      "Vendedora Pl Base Em Brasilia Df": 1,
      "Auxiliar Administrativo Financeiro": 1,
      "Promotor De Vendas Externas": 1,
      "Consultor Comercial": 1,
      "Assistente De Recursos Humanos": 2,
      "Operadora De Loja Brasilia Df": 1,
      "Tecnico De Seguranca Do Trabalho": 1,
      "Executivo De Vendas Externas": 2,
      "Vendedora": 1,
      "Recepcionista De Clinica Medica Sobradinho": 1,
      "Recepcionista De Clinica Medica Taguatinga": 1,
      "Gerente De Emporio": 1,
      "Assistente De Dp": 1,
      "Gerente Administrativo Em Salao De Beleza": 1,
      "Consultor Comercial Externo Brasilia": 1,
      "Assistente Comercial Ii Pcd Brasilia Df": 1,
      "Representante De Vendas Brasilia": 1,
      "Secretaria Comercial": 1,
      "Vendas De Acessorios De Celular": 2,
      "Consultor De Vendas Brasilia": 2,
      "Vendedor Externo Brasilia": 1,
      "Analista De Atendimento Jr Produtos Financeiros": 1,
      "Tecnico De Seguranca": 1,
      "Assistente De Vendas Cosmeticos Park Shopping Brasilia": 1,
      "Promotora De Vendas Externas Brasilia Df": 1,
      "Executivo De Contas Sr Seguros": 1,
      "Subgerente Comercial": 1,
      "Monitor De Caes Hospedagem E Creche": 1,
      "Corretor De Credito Consignado": 1,
      "Promotor De Vendas Jr": 1,
      "Vendedor De Loja": 2,
      "Operador De Monitoramento": 1,
      "Auxiliar De Prevencao E Perdas": 1,
      "Consultor De Vendas Estetica": 1,
      "Analista De Dp": 1,
      "Analista De Recursos Humanos": 1,
      "Assistente De Compras": 1,
      "Auxiliar De Limpeza Geral": 1,
      "Vaga Gerente Comercial Atuacao Df Go E Ma": 1,
      "Promotor De Trade Marketing I": 1,
      "Vendedor De Consorcio Interno": 1,
      "Consultora Comercial De Cirurgia Plastica": 1,
      "Vendedor Hering": 1,
      "Contabilista": 1,
      "Jardineiro": 1,
      "Assistente Recursos Humanos": 1,
      "Recepcionista Hospitalar": 1,
      "Consultor De Vendas Brasilia Df": 1,
      "Recepcionista Clinica Acesso Saude": 1,
      "Especialista Em Contratos Vaga Afirmativa Tambem Para O Publico Pcd 96613": 1,
      "Vendedor Multicoisas Lago Sul": 1,
      "Auxiliar Fiscal Contabil": 1,
      "Representante Comercial De Vendas": 1,
      "Vendedora De Loja Com Experiencia Em Otica Ou Oftalmologia Para Empresa No Sudoeste": 1,
      "Operador De Televendas Ativo": 2,
      "Supervisora Call Center Para Hospital Oftalmologico Asa Sul": 1,
      "Encarregado De Limpeza E Cuidado Animal": 1,
      "Lider De Equipe": 1,
      "Assistente De Loja Ii Balconista Asa Norte": 1,
      "Gerente De Loja Com Experiencia Em Otica E Oftalmologia Para Empresa No Sudoeste": 1,
      "Consultor Tecnico Comercial": 1,
      "Auxiliar De Compras": 1,
      "Fiscal De Caixa": 1,
      "Assistente De Vendas Comercial": 1,
      "Caixa Administrativo": 1,
      "Auxiliar Financeiro Administrativo": 1,
      "Recepcionista Administrativa": 1,
      "Auxiliar De Limpeza Hospitalar": 1,
      "Recepcionista De Clinica Medica": 1,
      "Gerente Comercial": 1,
      "Gerente De Vendas Clinica Dermatologica": 1,
      "Auxiliar De Limpeza": 1,
      "Analista De Suporte Middleware Jr": 1,
      "Analista De Suporte Middleware Pl": 1,
      "Controladoria E Suporte": 1,
      "Web Designer": 1,
      "Analista De Marketing Digital": 1,
      "Analista De Projeto Winthor Implantacao Wms Totvs": 1,
      "Assistente De Marketing Digital": 1,
      "Atendente De E Commerce": 1,
      "Diagramadora Escolar": 1,
      "Gerente De Marketing Digital": 1,
      "Tecnico Em Informatica": 1,
      "Estagio De Ti Matutino": 1,
      "Tecnico Saude Bucal": 1,
      "Supervisor De Call Center Ativo Com Experiencia Na Area Oftalmologica": 1,
      "Recepcionista Comercial Para Instituto De Estetica E Pos Graduacao Quality Hotel": 1,
      "Atendente Ao Cliente": 1,
      "Atendimento Ao Cliente": 1,
      "Atendente Vendedor": 1,
      "Atendente Saborella Gelato": 1,
      "Atendente La Paniere": 1,
      "Analista De Noc I Pcd Sao Paulo Sp": 1,
      "Analista De Infraestrutura Senior": 1,
      "Analista Infraestrutura Ti Pl Hospital Central De Alta Complexidade De Mato Grosso Cuiaba Mt": 1,
      "Analista De Telecomunicacao Pleno": 1,
      "Analista De Redes E Comunicacao De Dados": 1,
      "Tecnico De Infraestrutura De Ti": 1,
      "Analista De Suporte N2": 1,
      "Analista De Telecomunicacoes N2": 1,
      "Analista De Redes": 1,
      "Analista De Redes N2": 1,
      "Analista De Infraestrutura Ti": 1,
      "Tecnico De Infraestrutura": 3,
      "Analista Tecnico Junior": 1,
      "Analista De Rede De Comunicacao De Dados Senior": 1,
      "Sondador": 1,
      "Encarregado De Manutencao": 1,
      "Vendedor De Acessorios Automotivos": 1,
      "Tecnico Em Eletromecanica": 1,
      "Tecnico De Refrigeracao": 1,
      "Tecnico De Edificacao": 1,
      "Tecnico De Manutencao De Ar Condicionado": 1,
      "Operadora De Estacao De Tratamento De Efluentes 97911": 1,
      "Tecnico De Campo Ti": 1,
      "Tecnico Em Mecanica": 1,
      "Tecnico Em Secretariado": 1,
      "Auxiliar De Logistica": 2,
      "Auxiliar De Entrega": 1,
      "Motorista Com Carteira D Para Empresa De Colchoes E Mobiliario Em Taguatinga Df": 1,
      "Supervisor De Operacoes": 1,
      "Motorista Entregador Abastecedor Vaga Afirmativa Tambem Para O Publico Pcd 99546": 1,
      "Ajudante Entrega Vaga Afirmativa Tambem Para O Publico Pcd 99607": 1,
      "Auxiliar De Logistica Separador": 1,
      "Ajudante De Carga E Descarga Vaga Afirmativa Tambem Para O Publico Pcd 99161": 1,
      "Estoquista De Loja": 1,
      "Assistente De Logistica": 1,
      "Ajudante De Expedicao Vaga Afirmativa Tambem Para O Publico Pcd 99102": 1,
      "Ajudante De Motorista": 1,
      "Operador De Logistica": 1,
      "Assistente Farmaceutico": 1,
      "Auxiliar De Saude Bucal": 2,
      "Massoterapeuta": 1,
      "Nutricionista": 1,
      "Professora De Musculacao": 1,
      "Analista Juridico Pleno": 1,
      "Especialista De Fidc Fundo De Investimento Em Direitos Creditorios": 1,
      "Analista De Licitacao Publica": 1,
      "Assistente Juridico": 5,
      "Advogado A Direito De Familia": 1,
      "Analista De Certificacoes E Propriedade Intelectual Inpi Inmetro Anvisa Anatel": 1,
      "Advogado Senior": 1,
      "Tecnico Em Instalacao E Manutencao": 1,
      "Tecnico De Manutencao E Instalacao Sharp1067": 1,
      "Oficial De Manutencao Civil": 1,
      "Farmaceutico A": 1,
      "Auxiliar De Manutencao Predial": 1,
      "Oficial De Manutencao Predial": 1,
      "Corretor De Seguros": 1,
      "Assistente Fiscal Contabil": 1,
      "Assistente De Administrativo Hospitalar": 1,
      "Auxiliar De Contas Medicas": 1,
      "Auxiliar Administrativo Hospitalar": 1,
      "Auxiliar De Contas Medicas Hospitalar": 1,
      "Analista De Contas Medicas Hospitalar": 1,
      "Operador De Caixa": 2,
      "Auxiliar Administrativo Brasilia Df": 1,
      "Assistente Legalizacao De Empresas": 1,
      "Analista De Matricula": 1,
      "Assistente Financeiro": 1,
      "Tecnico Eletricista": 1,
      "Tecnico Eletronico": 1,
      "Tecnico Eletrotecnico": 1,
      "Operador De Maquina": 1,
      "Auxiliar De Engenharia Civil": 2,
      "Medidor De Marmoraria": 1,
      "Auxiliar Tecnico Em Laboratorio De Farmacia": 1,
      "Engenheiro Civil": 1,
      "Orcamentista Civil": 1,
      "Professor Bilingue Ingles": 1,
      "Instrutor De Natacao Kids Sudoeste Df": 1,
      "Instrutora De Judo Sudoeste Df": 1,
      "Coordenador De Curso Rt": 1,
      "Revisor De Textos": 1,
      "Professor Ead": 1,
      "Consultor Pedagogico": 1,
      "Designer Instrucional": 1,
      "Professor De Ginastica Laboral": 1,
      "Instrutor De Ginastica Laboral": 1,
      "Instrutora De Natacao Baby Asa Sul Df": 1,
      "Instrutora De Circo Asa Sul Df": 1,
      "Auxiliar De Sala": 1,
      "Analista De Treinamento Jr": 1,
      "Auxiliar De Vendas": 1,
      "Tutor De Vendas": 1
    },
    "total_responsabilidades_unicas": 9,
    "total_habilidades_unicas": 21
  },
  "exemplos_separacao": [
    {
      "id": 1,
      "titulo": "Ajudante Geral",
      "responsabilidades_count": 1,
      "habilidades_count": 3,
      "descricao_preview": "Vaga: Ajudante Geral | Responsabilidades: EMPRESA DE MÁQUINAS DE COSTURA - SKY TEC Receber e conferi..."
    },
    {
      "id": 2,
      "titulo": "Coordenadora De Projeto Social",
      "responsabilidades_count": 1,
      "habilidades_count": 3,
      "descricao_preview": "Vaga: Coordenadora De Projeto Social | Responsabilidades: Planejar, implementar e monitorar projetos..."
    },
    {
      "id": 3,
      "titulo": "Assistente Social",
      "responsabilidades_count": 1,
      "habilidades_count": 3,
      "descricao_preview": "Vaga: Assistente Social | Responsabilidades: Entrevistar por telefone e em visita, quando necessário..."
    }
  ]
}